ohsome_filter_to_sql/OFLLexer.py
ohsome_filter_to_sql/OFLListener.py
ohsome_filter_to_sql/OFLParser.py
ohsome_filter_to_sql/__init__.py
ohsome_filter_to_sql/main.py
ohsome_filter_to_sql-0.3.0.dist-info/licenses/COPYING
ohsome_filter_to_sql-0.3.0.dist-info/licenses/COPYING.LESSER
ohsome_filter_to_sql-0.3.0.dist-info/WHEEL
ohsome_filter_to_sql-0.3.0.dist-info/entry_points.txt
ohsome_filter_to_sql-0.3.0.dist-info/METADATA
ohsome_filter_to_sql-0.3.0.dist-info/RECORD
