Metadata-Version: 2.4
Name: ohsome-filter-to-sql
Version: 0.3.0
Summary: Translate ohsome API filter to SQL WHERE clause ready to be used with ohsomeDB
Author: HeiGIT ohsome team
Author-email: HeiGIT ohsome team <ohsome@heigit.org>
License-Expression: LGPL-3.0-only
License-File: COPYING
License-File: COPYING.LESSER
Classifier: Intended Audience :: Developers
Classifier: Intended Audience :: Science/Research
Classifier: License :: OSI Approved :: GNU Lesser General Public License v3 (LGPLv3)
Classifier: Programming Language :: Python :: 3 :: Only
Classifier: Programming Language :: Python :: 3.11
Classifier: Programming Language :: Python :: 3.12
Classifier: Programming Language :: Python :: 3.13
Classifier: Topic :: Scientific/Engineering :: GIS
Classifier: Topic :: Software Development :: Libraries :: Python Modules
Requires-Dist: antlr4-python3-runtime>=4.13.2
Requires-Dist: pydantic>=2.12.5
Requires-Python: >=3.11, <3.14
Project-URL: Documentation, https://github.com/GIScience/ohsome-filter-to-sql/blob/main/README.md
Project-URL: Homepage, https://ohsome.org/
Project-URL: Issues, https://github.com/GIScience/ohsome-filter-to-sql/issues
Project-URL: Repository, https://github.com/GIScience/ohsome-filter-to-sql
